gspc/__init__.py
gspc/main.py
gspc/core/__init__.py
gspc/core/atom.py
gspc/core/box.py
gspc/core/cutoff.py
gspc/core/system.py
gspc/data/__init__.py
gspc/extensions/NSx.py
gspc/extensions/SiO2.py
gspc/extensions/__init__.py
gspc/io/__init__.py
gspc/io/make_lines_unique.py
gspc/io/read_and_create_system.py
gspc/io/read_lattice_properties.py
gspc/io/read_number_of_configurations.py
gspc/io/result.py
gspc/io/write_list_of_files.py
gspc/settings/__init__.py
gspc/settings/parameter.py
gspc/settings/settings.py
gspc/utils/__init__.py
gspc/utils/generate_color_gradient.py
gspc/utils/generate_recaps.py
gspc/utils/print_title.py
gspc-0.0.22.dist-info/METADATA
gspc-0.0.22.dist-info/WHEEL
gspc-0.0.22.dist-info/top_level.txt
gspc-0.0.22.dist-info/RECORD
