Metadata-Version: 2.1
Name: gspc
Version: 0.0.22
Summary: GSPC package is a package for computing structural properties of glasses
Home-page: https://github.com/JulienPerradin/gspc
Author: Julien Perradin
Author-email: julien.perradin@umontpellier.fr
Requires-Dist: numpy
Requires-Dist: pandas
Requires-Dist: matplotlib
Requires-Dist: numba
Requires-Dist: numba-progress
Requires-Dist: scipy
